oci_client/__init__.py
oci_client/_client.py
oci_client/_helpers.py
oci_client/_services.py
oci_client/bundled/endpoints.json
oci_client/cfg.py
oci_client/client.py
oci_client/py.typed
oci_client-0.3.2.dist-info/LICENSE
oci_client-0.3.2.dist-info/METADATA
oci_client-0.3.2.dist-info/WHEEL
oci_client-0.3.2.dist-info/RECORD
